data_struct/__init__.py
data_struct/basic.py
dstwo-1.0.0.dist-info/METADATA
dstwo-1.0.0.dist-info/WHEEL
dstwo-1.0.0.dist-info/top_level.txt
dstwo-1.0.0.dist-info/RECORD
