Metadata-Version: 2.1
Name: dstwo
Version: 1.0.0
Summary: Basic data structures and algorithms
Home-page: UNKNOWN
Author: Reny
Author-email: Rjs3175@aliyun.com
License: UNKNOWN
Platform: UNKNOWN
